libgossip/__main__.py
libgossip/libgossip_py.cpython-311-x86_64-linux-gnu.so
libgossip/__init__.py
libgossip/sdk_example.py
libgossip/decorator_example.py
libgossip-0.2.1.dist-info/METADATA
libgossip-0.2.1.dist-info/top_level.txt
libgossip-0.2.1.dist-info/WHEEL
libgossip-0.2.1.dist-info/RECORD
