Metadata-Version: 2.4
Name: libgossip
Version: 0.2.1
Summary: Python bindings for libgossip - a C++ Gossip protocol implementation
Author-email: caomengxuan666 <caomengxuan666@gmail.com>
License: MIT
Project-URL: Homepage, https://github.com/caomengxuan666/libgossip
Project-URL: Repository, https://github.com/caomengxuan666/libgossip
Classifier: Development Status :: 3 - Alpha
Classifier: Intended Audience :: Developers
Classifier: License :: OSI Approved :: MIT License
Classifier: Programming Language :: Python :: 3
Classifier: Programming Language :: Python :: 3.8
Classifier: Programming Language :: Python :: 3.9
Classifier: Programming Language :: Python :: 3.10
Classifier: Programming Language :: Python :: 3.11
Classifier: Programming Language :: Python :: 3.12
Classifier: Programming Language :: Python :: 3.13
Classifier: Programming Language :: Python :: 3.14
Requires-Python: >=3.8
Requires-Dist: pybind11>=3.0.0
Provides-Extra: test
Requires-Dist: pytest; extra == "test"
Dynamic: requires-python
